AdNoise/AdversarialNoise.py
AdNoise/AttackMethods.py
AdNoise/__init__.py
AdNoise-0.1.0.dist-info/METADATA
AdNoise-0.1.0.dist-info/WHEEL
AdNoise-0.1.0.dist-info/top_level.txt
AdNoise-0.1.0.dist-info/RECORD
